mimelib/__init__.py
mimelib/__version__.py
mimelib/known.py
mimelib/lib.py
mimelib-0.1.1.dist-info/METADATA
mimelib-0.1.1.dist-info/RECORD
mimelib-0.1.1.dist-info/WHEEL
mimelib-0.1.1.dist-info/top_level.txt
